{
  "TagName": "objects\\weapons\\grenade\\claymore_grenade\\claymore_grenade",
  "TagType": "collision_model",
  "Generate": false,
  "TagVersion": "HaloOnlineED",
  "Bitmaps": null,
  "Animations": null,
  "RenderGeometry": null,
  "BlamScriptResource": null,
  "StructureBsp": null,
  "Sounds": null,
  "UnicodeStrings": null,
  "TagData": {
    "CollisionModelChecksum": 286723094,
    "Flags": "None",
    "Materials": [
      {
        "Name": "hard_metal_thin_hum"
      }
    ],
    "Regions": [
      {
        "Name": "default",
        "Permutations": [
          {
            "Name": "default",
            "Bsps": [
              {
                "NodeIndex": 0,
                "Geometry": {
                  "Bsp3dNodes": [
                    {
                      "Value": 9223381932459491328
                    },
                    {
                      "Value": 9223380832947929097
                    },
                    {
                      "Value": 9223379733436366849
                    },
                    {
                      "Value": 9223378633924804610
                    },
                    {
                      "Value": 9223377534413242371
                    },
                    {
                      "Value": 9223376434901680132
                    },
                    {
                      "Value": 9223375335390117893
                    },
                    {
                      "Value": 9223374235878555654
                    },
                    {
                      "Value": 9223373136366993415
                    },
                    {
                      "Value": 9223373136366338056
                    }
                  ],
                  "Planes": [
                    {
                      "Value": " Normal: I: -0.99983877, J: 0.017282944, K: -0.0048663924, Distance:  0.2763591"
                    },
                    {
                      "Value": " Normal: I: -0.0739635, J: 0.26779193, K: -0.9606336, Distance:  0.046070594"
                    },
                    {
                      "Value": " Normal: I: -0.065862454, J: 0.8686854, K: -0.49096617, Distance:  0.041890636"
                    },
                    {
                      "Value": " Normal: I: -0.06794134, J: 0.9615577, K: 0.26606533, Distance:  0.036423277"
                    },
                    {
                      "Value": " Normal: I: -0.07898237, J: 0.4920055, K: 0.86700195, Distance:  0.032871228"
                    },
                    {
                      "Value": " Normal: I: -0.09251784, J: -0.26491416, K: 0.95982337, Distance:  0.033315226"
                    },
                    {
                      "Value": " Normal: I: -0.10061886, J: -0.8658078, K: 0.49015585, Distance:  0.037495185"
                    },
                    {
                      "Value": " Normal: I: -0.09853996, J: -0.95868, K: -0.26687565, Distance:  0.04296254"
                    },
                    {
                      "Value": " Normal: I: -0.08749896, J: -0.48912778, K: -0.86781216, Distance:  0.046514593"
                    },
                    {
                      "Value": " Normal: I: 0.9998388, J: -0.01728272, K: 0.004865905, Distance:  0.0042138384"
                    }
                  ],
                  "Leaves": [
                    {
                      "Flags": "None",
                      "Flags2": "None",
                      "Bsp2dReferenceCount": 1,
                      "FirstBsp2dReference": 0
                    },
                    {
                      "Flags": "None",
                      "Flags2": "None",
                      "Bsp2dReferenceCount": 1,
                      "FirstBsp2dReference": 1
                    },
                    {
                      "Flags": "None",
                      "Flags2": "None",
                      "Bsp2dReferenceCount": 1,
                      "FirstBsp2dReference": 2
                    },
                    {
                      "Flags": "None",
                      "Flags2": "None",
                      "Bsp2dReferenceCount": 1,
                      "FirstBsp2dReference": 3
                    },
                    {
                      "Flags": "None",
                      "Flags2": "None",
                      "Bsp2dReferenceCount": 1,
                      "FirstBsp2dReference": 4
                    },
                    {
                      "Flags": "None",
                      "Flags2": "None",
                      "Bsp2dReferenceCount": 1,
                      "FirstBsp2dReference": 5
                    },
                    {
                      "Flags": "None",
                      "Flags2": "None",
                      "Bsp2dReferenceCount": 1,
                      "FirstBsp2dReference": 6
                    },
                    {
                      "Flags": "None",
                      "Flags2": "None",
                      "Bsp2dReferenceCount": 1,
                      "FirstBsp2dReference": 7
                    },
                    {
                      "Flags": "None",
                      "Flags2": "None",
                      "Bsp2dReferenceCount": 1,
                      "FirstBsp2dReference": 8
                    },
                    {
                      "Flags": "None",
                      "Flags2": "None",
                      "Bsp2dReferenceCount": 1,
                      "FirstBsp2dReference": 9
                    }
                  ],
                  "Bsp2dReferences": [
                    {
                      "PlaneIndex": 8,
                      "Bsp2dNodeIndex": -32757
                    },
                    {
                      "PlaneIndex": 7,
                      "Bsp2dNodeIndex": -32758
                    },
                    {
                      "PlaneIndex": 6,
                      "Bsp2dNodeIndex": -32759
                    },
                    {
                      "PlaneIndex": 5,
                      "Bsp2dNodeIndex": -32760
                    },
                    {
                      "PlaneIndex": 4,
                      "Bsp2dNodeIndex": -32761
                    },
                    {
                      "PlaneIndex": 3,
                      "Bsp2dNodeIndex": -32762
                    },
                    {
                      "PlaneIndex": 2,
                      "Bsp2dNodeIndex": -32763
                    },
                    {
                      "PlaneIndex": 1,
                      "Bsp2dNodeIndex": -32764
                    },
                    {
                      "PlaneIndex": 9,
                      "Bsp2dNodeIndex": 0
                    },
                    {
                      "PlaneIndex": 0,
                      "Bsp2dNodeIndex": 3
                    }
                  ],
                  "Bsp2dNodes": [
                    {
                      "Plane": "Normal: I: 0.1217187, J: 0.9925646, Distance: -0.0071568172",
                      "LeftChild": 1,
                      "RightChild": 2
                    },
                    {
                      "Plane": "Normal: I: -0.6158227, J: 0.7878847, Distance: -0.004595655",
                      "LeftChild": -32756,
                      "RightChild": -32753
                    },
                    {
                      "Plane": "Normal: I: -0.6158226, J: 0.7878848, Distance: -0.0045956555",
                      "LeftChild": -32755,
                      "RightChild": -32754
                    },
                    {
                      "Plane": "Normal: I: 0.12176672, J: -0.9925587, Distance: -0.0043224003",
                      "LeftChild": 4,
                      "RightChild": 5
                    },
                    {
                      "Plane": "Normal: I: 0.78788495, J: -0.6158225, Distance: -0.008657471",
                      "LeftChild": -32768,
                      "RightChild": -32767
                    },
                    {
                      "Plane": "Normal: I: -0.7878849, J: 0.6158225, Distance: 0.008657471",
                      "LeftChild": -32766,
                      "RightChild": -32765
                    }
                  ],
                  "Surfaces": [
                    {
                      "Plane": 0,
                      "FirstEdge": 0,
                      "MaterialIndex": 0,
                      "BreakableSurfaceSet": -1,
                      "BreakableSurfaceIndex": -1,
                      "Flags": "None",
                      "BestPlaneCalculationVertex": 0
                    },
                    {
                      "Plane": 0,
                      "FirstEdge": 3,
                      "MaterialIndex": 0,
                      "BreakableSurfaceSet": -1,
                      "BreakableSurfaceIndex": -1,
                      "Flags": "None",
                      "BestPlaneCalculationVertex": 0
                    },
                    {
                      "Plane": 0,
                      "FirstEdge": 5,
                      "MaterialIndex": 0,
                      "BreakableSurfaceSet": -1,
                      "BreakableSurfaceIndex": -1,
                      "Flags": "None",
                      "BestPlaneCalculationVertex": 0
                    },
                    {
                      "Plane": 0,
                      "FirstEdge": 1,
                      "MaterialIndex": 0,
                      "BreakableSurfaceSet": -1,
                      "BreakableSurfaceIndex": -1,
                      "Flags": "None",
                      "BestPlaneCalculationVertex": 0
                    },
                    {
                      "Plane": 1,
                      "FirstEdge": 0,
                      "MaterialIndex": 0,
                      "BreakableSurfaceSet": -1,
                      "BreakableSurfaceIndex": -1,
                      "Flags": "None",
                      "BestPlaneCalculationVertex": 0
                    },
                    {
                      "Plane": 2,
                      "FirstEdge": 14,
                      "MaterialIndex": 0,
                      "BreakableSurfaceSet": -1,
                      "BreakableSurfaceIndex": -1,
                      "Flags": "None",
                      "BestPlaneCalculationVertex": 0
                    },
                    {
                      "Plane": 3,
                      "FirstEdge": 16,
                      "MaterialIndex": 0,
                      "BreakableSurfaceSet": -1,
                      "BreakableSurfaceIndex": -1,
                      "Flags": "None",
                      "BestPlaneCalculationVertex": 0
                    },
                    {
                      "Plane": 4,
                      "FirstEdge": 18,
                      "MaterialIndex": 0,
                      "BreakableSurfaceSet": -1,
                      "BreakableSurfaceIndex": -1,
                      "Flags": "None",
                      "BestPlaneCalculationVertex": 0
                    },
                    {
                      "Plane": 5,
                      "FirstEdge": 20,
                      "MaterialIndex": 0,
                      "BreakableSurfaceSet": -1,
                      "BreakableSurfaceIndex": -1,
                      "Flags": "None",
                      "BestPlaneCalculationVertex": 0
                    },
                    {
                      "Plane": 6,
                      "FirstEdge": 22,
                      "MaterialIndex": 0,
                      "BreakableSurfaceSet": -1,
                      "BreakableSurfaceIndex": -1,
                      "Flags": "None",
                      "BestPlaneCalculationVertex": 0
                    },
                    {
                      "Plane": 7,
                      "FirstEdge": 24,
                      "MaterialIndex": 0,
                      "BreakableSurfaceSet": -1,
                      "BreakableSurfaceIndex": -1,
                      "Flags": "None",
                      "BestPlaneCalculationVertex": 0
                    },
                    {
                      "Plane": 8,
                      "FirstEdge": 26,
                      "MaterialIndex": 0,
                      "BreakableSurfaceSet": -1,
                      "BreakableSurfaceIndex": -1,
                      "Flags": "None",
                      "BestPlaneCalculationVertex": 0
                    },
                    {
                      "Plane": 9,
                      "FirstEdge": 12,
                      "MaterialIndex": 0,
                      "BreakableSurfaceSet": -1,
                      "BreakableSurfaceIndex": -1,
                      "Flags": "None",
                      "BestPlaneCalculationVertex": 0
                    },
                    {
                      "Plane": 9,
                      "FirstEdge": 17,
                      "MaterialIndex": 0,
                      "BreakableSurfaceSet": -1,
                      "BreakableSurfaceIndex": -1,
                      "Flags": "None",
                      "BestPlaneCalculationVertex": 0
                    },
                    {
                      "Plane": 9,
                      "FirstEdge": 19,
                      "MaterialIndex": 0,
                      "BreakableSurfaceSet": -1,
                      "BreakableSurfaceIndex": -1,
                      "Flags": "None",
                      "BestPlaneCalculationVertex": 0
                    },
                    {
                      "Plane": 9,
                      "FirstEdge": 25,
                      "MaterialIndex": 0,
                      "BreakableSurfaceSet": -1,
                      "BreakableSurfaceIndex": -1,
                      "Flags": "None",
                      "BestPlaneCalculationVertex": 0
                    }
                  ],
                  "Edges": [
                    {
                      "StartVertex": 1,
                      "EndVertex": 2,
                      "ForwardEdge": 1,
                      "ReverseEdge": 14,
                      "LeftSurface": 0,
                      "RightSurface": 4
                    },
                    {
                      "StartVertex": 2,
                      "EndVertex": 0,
                      "ForwardEdge": 3,
                      "ReverseEdge": 11,
                      "LeftSurface": 0,
                      "RightSurface": 3
                    },
                    {
                      "StartVertex": 3,
                      "EndVertex": 1,
                      "ForwardEdge": 0,
                      "ReverseEdge": 16,
                      "LeftSurface": 0,
                      "RightSurface": 5
                    },
                    {
                      "StartVertex": 0,
                      "EndVertex": 4,
                      "ForwardEdge": 4,
                      "ReverseEdge": 5,
                      "LeftSurface": 0,
                      "RightSurface": 1
                    },
                    {
                      "StartVertex": 4,
                      "EndVertex": 3,
                      "ForwardEdge": 2,
                      "ReverseEdge": 18,
                      "LeftSurface": 0,
                      "RightSurface": 6
                    },
                    {
                      "StartVertex": 0,
                      "EndVertex": 5,
                      "ForwardEdge": 6,
                      "ReverseEdge": 9,
                      "LeftSurface": 1,
                      "RightSurface": 2
                    },
                    {
                      "StartVertex": 5,
                      "EndVertex": 4,
                      "ForwardEdge": 3,
                      "ReverseEdge": 20,
                      "LeftSurface": 1,
                      "RightSurface": 7
                    },
                    {
                      "StartVertex": 6,
                      "EndVertex": 5,
                      "ForwardEdge": 5,
                      "ReverseEdge": 22,
                      "LeftSurface": 2,
                      "RightSurface": 8
                    },
                    {
                      "StartVertex": 7,
                      "EndVertex": 6,
                      "ForwardEdge": 7,
                      "ReverseEdge": 24,
                      "LeftSurface": 2,
                      "RightSurface": 9
                    },
                    {
                      "StartVertex": 0,
                      "EndVertex": 8,
                      "ForwardEdge": 10,
                      "ReverseEdge": 1,
                      "LeftSurface": 2,
                      "RightSurface": 3
                    },
                    {
                      "StartVertex": 8,
                      "EndVertex": 7,
                      "ForwardEdge": 8,
                      "ReverseEdge": 26,
                      "LeftSurface": 2,
                      "RightSurface": 10
                    },
                    {
                      "StartVertex": 2,
                      "EndVertex": 8,
                      "ForwardEdge": 9,
                      "ReverseEdge": 13,
                      "LeftSurface": 3,
                      "RightSurface": 11
                    },
                    {
                      "StartVertex": 9,
                      "EndVertex": 10,
                      "ForwardEdge": 13,
                      "ReverseEdge": 15,
                      "LeftSurface": 4,
                      "RightSurface": 12
                    },
                    {
                      "StartVertex": 10,
                      "EndVertex": 2,
                      "ForwardEdge": 0,
                      "ReverseEdge": 27,
                      "LeftSurface": 4,
                      "RightSurface": 11
                    },
                    {
                      "StartVertex": 1,
                      "EndVertex": 9,
                      "ForwardEdge": 12,
                      "ReverseEdge": 2,
                      "LeftSurface": 4,
                      "RightSurface": 5
                    },
                    {
                      "StartVertex": 11,
                      "EndVertex": 9,
                      "ForwardEdge": 14,
                      "ReverseEdge": 28,
                      "LeftSurface": 5,
                      "RightSurface": 12
                    },
                    {
                      "StartVertex": 3,
                      "EndVertex": 11,
                      "ForwardEdge": 15,
                      "ReverseEdge": 4,
                      "LeftSurface": 5,
                      "RightSurface": 6
                    },
                    {
                      "StartVertex": 12,
                      "EndVertex": 11,
                      "ForwardEdge": 16,
                      "ReverseEdge": 29,
                      "LeftSurface": 6,
                      "RightSurface": 13
                    },
                    {
                      "StartVertex": 4,
                      "EndVertex": 12,
                      "ForwardEdge": 17,
                      "ReverseEdge": 6,
                      "LeftSurface": 6,
                      "RightSurface": 7
                    },
                    {
                      "StartVertex": 13,
                      "EndVertex": 12,
                      "ForwardEdge": 18,
                      "ReverseEdge": 21,
                      "LeftSurface": 7,
                      "RightSurface": 14
                    },
                    {
                      "StartVertex": 5,
                      "EndVertex": 13,
                      "ForwardEdge": 19,
                      "ReverseEdge": 7,
                      "LeftSurface": 7,
                      "RightSurface": 8
                    },
                    {
                      "StartVertex": 14,
                      "EndVertex": 13,
                      "ForwardEdge": 20,
                      "ReverseEdge": 23,
                      "LeftSurface": 8,
                      "RightSurface": 14
                    },
                    {
                      "StartVertex": 6,
                      "EndVertex": 14,
                      "ForwardEdge": 21,
                      "ReverseEdge": 8,
                      "LeftSurface": 8,
                      "RightSurface": 9
                    },
                    {
                      "StartVertex": 15,
                      "EndVertex": 14,
                      "ForwardEdge": 22,
                      "ReverseEdge": 30,
                      "LeftSurface": 9,
                      "RightSurface": 14
                    },
                    {
                      "StartVertex": 7,
                      "EndVertex": 15,
                      "ForwardEdge": 23,
                      "ReverseEdge": 10,
                      "LeftSurface": 9,
                      "RightSurface": 10
                    },
                    {
                      "StartVertex": 16,
                      "EndVertex": 15,
                      "ForwardEdge": 24,
                      "ReverseEdge": 31,
                      "LeftSurface": 10,
                      "RightSurface": 15
                    },
                    {
                      "StartVertex": 8,
                      "EndVertex": 16,
                      "ForwardEdge": 25,
                      "ReverseEdge": 11,
                      "LeftSurface": 10,
                      "RightSurface": 11
                    },
                    {
                      "StartVertex": 10,
                      "EndVertex": 16,
                      "ForwardEdge": 26,
                      "ReverseEdge": 12,
                      "LeftSurface": 11,
                      "RightSurface": 12
                    },
                    {
                      "StartVertex": 11,
                      "EndVertex": 17,
                      "ForwardEdge": 31,
                      "ReverseEdge": 17,
                      "LeftSurface": 12,
                      "RightSurface": 13
                    },
                    {
                      "StartVertex": 12,
                      "EndVertex": 17,
                      "ForwardEdge": 28,
                      "ReverseEdge": 19,
                      "LeftSurface": 13,
                      "RightSurface": 14
                    },
                    {
                      "StartVertex": 15,
                      "EndVertex": 17,
                      "ForwardEdge": 29,
                      "ReverseEdge": 25,
                      "LeftSurface": 14,
                      "RightSurface": 15
                    },
                    {
                      "StartVertex": 16,
                      "EndVertex": 17,
                      "ForwardEdge": 30,
                      "ReverseEdge": 27,
                      "LeftSurface": 15,
                      "RightSurface": 12
                    }
                  ],
                  "Vertices": [
                    {
                      "Point": "X: -0.27630535, Y: 0.0033256637, Z: -0.0083888555",
                      "FirstEdge": 3,
                      "Sink": 0
                    },
                    {
                      "Point": "X: -0.276043, Y: 0.014482552, Z: -0.02266752",
                      "FirstEdge": 0,
                      "Sink": 0
                    },
                    {
                      "Point": "X: -0.27625594, Y: 0.001118954, Z: -0.02637644",
                      "FirstEdge": 1,
                      "Sink": 0
                    },
                    {
                      "Point": "X: -0.27598372, Y: 0.021310592, Z: -0.010594355",
                      "FirstEdge": 2,
                      "Sink": 0
                    },
                    {
                      "Point": "X: -0.27611285, Y: 0.017603308, Z: 0.002770762",
                      "FirstEdge": 4,
                      "Sink": 0
                    },
                    {
                      "Point": "X: -0.27635476, Y: 0.0055323737, Z: 0.009598729",
                      "FirstEdge": 6,
                      "Sink": 0
                    },
                    {
                      "Point": "X: -0.2765677, Y: -0.007831222, Z: 0.0058898106",
                      "FirstEdge": 7,
                      "Sink": 0
                    },
                    {
                      "Point": "X: -0.27662694, Y: -0.014659263, Z: -0.006183358",
                      "FirstEdge": 8,
                      "Sink": 0
                    },
                    {
                      "Point": "X: -0.27649784, Y: -0.010951979, Z: -0.019548472",
                      "FirstEdge": 10,
                      "Sink": 0
                    },
                    {
                      "Point": "X: 0.004851988, Y: 0.025253123, Z: -0.041292418",
                      "FirstEdge": 12,
                      "Sink": 0
                    },
                    {
                      "Point": "X: 0.004340917, Y: -0.0068195006, Z: -0.050193824",
                      "FirstEdge": 13,
                      "Sink": 0
                    },
                    {
                      "Point": "X: 0.0049942355, Y: 0.041640423, Z: -0.012316816",
                      "FirstEdge": 15,
                      "Sink": 0
                    },
                    {
                      "Point": "X: 0.0046843328, Y: 0.03274294, Z: 0.019759472",
                      "FirstEdge": 17,
                      "Sink": 0
                    },
                    {
                      "Point": "X: 0.0041038166, Y: 0.003772702, Z: 0.036146592",
                      "FirstEdge": 19,
                      "Sink": 0
                    },
                    {
                      "Point": "X: 0.0035927452, Y: -0.028299924, Z: 0.027245188",
                      "FirstEdge": 21,
                      "Sink": 0
                    },
                    {
                      "Point": "X: 0.0034504978, Y: -0.044687223, Z: -0.0017304184",
                      "FirstEdge": 23,
                      "Sink": 0
                    },
                    {
                      "Point": "X: 0.0037604007, Y: -0.035789736, Z: -0.033806704",
                      "FirstEdge": 25,
                      "Sink": 0
                    },
                    {
                      "Point": "X: 0.0042223665, Y: -0.0015233989, Z: -0.0070236144",
                      "FirstEdge": 31,
                      "Sink": 0
                    }
                  ]
                }
              }
            ],
            "BspPhysics": [],
            "BspMoppCodes": []
          }
        ]
      }
    ],
    "PathfindingSpheres": [
      {
        "Node": 0,
        "Flags": "None",
        "Center": "X: -0.1, Y: 0, Z: 0",
        "Radius": 0.25
      }
    ],
    "Nodes": [
      {
        "Name": "node",
        "Flags": "None",
        "ParentNode": -1,
        "NextSiblingNode": -1,
        "FirstChildNode": -1
      }
    ]
  }
}