{
  "TagName": "ui\\halox\\start_menu\\animations\\sidebar\\sidebar_load3",
  "TagType": "gui_widget_position_animation_definition",
  "TagVersion": "HaloOnlineED",
  "Bitmaps": null,
  "Animations": null,
  "RenderGeometry": null,
  "BlamScriptResource": null,
  "StructureBsp": null,
  "Sounds": null,
  "UnicodeStrings": null,
  "TagData": {
    "Flags": "0",
    "Keyframes": [
      {
        "TimeOffset": 0,
        "Position": "X: 0, Y: 0, Z: 0",
        "CustomTransitionFxn": []
      },
      {
        "TimeOffset": 200,
        "Position": "X: 0, Y: -160, Z: 0",
        "CustomTransitionFxn": []
      },
      {
        "TimeOffset": 500,
        "Position": "X: 0, Y: -160, Z: 0",
        "CustomTransitionFxn": []
      }
    ],
    "Function": {
      "Data": "CDQAAAAAAAAAAIA/AAAAAAAAAAAAAAAAAAAAABwAAAABAAAABwAAzf//f38AAADAAABAQAAAAAAAAAAA"
    }
  }
}