{
  "TagName": "objects\\vehicles\\phantom\\phantom_damaged\\garbage\\phantom_chunk_04\\phantom_chunk_04",
  "TagType": "physics_model",
  "TagVersion": "HaloOnlineED",
  "Bitmaps": null,
  "Animations": null,
  "RenderGeometry": null,
  "BlamScriptResource": null,
  "StructureBsp": null,
  "Sounds": null,
  "UnicodeStrings": null,
  "TagData": {
    "Flags": "None",
    "Mass": 526.4932,
    "LowFrequencyDeactivationScale": 1.0,
    "HighFrequencyDeactivationScale": 1.0,
    "CustomShapeRadius": 0.0,
    "MaximumPenetrationDepthScale": 0.0,
    "ImportVersion": 1,
    "DampedSpringMotors": [],
    "PositionMotors": [],
    "PhantomTypes": [],
    "PoweredChains": [],
    "NodeEdges": [],
    "RigidBodies": [
      {
        "Node": 0,
        "Region": 0,
        "Permutation": 0,
        "SerializedShapes": 0,
        "BoundingSphereOffset": "X: 0, Y: 0, Z: 0",
        "BoundingSphereRadius": 0.7370668,
        "Flags": "None",
        "MotionType": "Box",
        "NoPhantomPowerAltRigidBody": -1,
        "Size": "Large",
        "InertiaTensorScale": 1.0,
        "LinearDampening": 0.0,
        "AngularDampening": 0.05,
        "CenterOfMassOffset": "I: 0, J: 0, K: 0",
        "WaterPhysicsX0": 0.0,
        "WaterPhysicsX1": 0.0,
        "WaterPhysicsY0": 0.0,
        "WaterPhysicsY1": 0.0,
        "WaterPhysicsZ0": 0.0,
        "WaterPhysicsZ1": 0.0,
        "RuntimeShapePointer": 0,
        "Unknown9": 0,
        "ShapeType": "Polyhedron",
        "ShapeIndex": 0,
        "Mass": 526.4932,
        "CenterOfMass": "I: 0.02404052, J: 0.11979319, K: -0.0073676934",
        "CenterOfMassRadius": 0.0,
        "InertiaTensorX": "I: 19.586649, J: -5.453435, K: 1.1298461",
        "InertiaTensorXRadius": 0.0,
        "InertiaTensorY": "I: -5.453435, J: 40.248135, K: 0.7916814",
        "InertiaTensorYRadius": 0.0,
        "InertiaTensorZ": "I: 1.1298461, J: 0.7916814, K: 58.119328",
        "InertiaTensorZRadius": 0.0,
        "CollisionGroupMask": 0,
        "Unknown10": 0,
        "BoundingSpherePad": 0.0,
        "CollisionQualityOverrideType": 0,
        "RuntimeFlags": 0
      }
    ],
    "Materials": [
      {
        "Name": "hard_metal_thick_cov",
        "MaterialName": "invalid",
        "PhantomType": -1,
        "ProxyCollisionGroup": 0,
        "RuntimeCollisionGroup": 255
      }
    ],
    "Spheres": [],
    "Pills": [],
    "Boxes": [],
    "Triangles": [],
    "Polyhedra": [
      {
        "Name": "phantom_chunk_04",
        "MaterialIndex": 0,
        "RuntimeMaterialType": 76,
        "RelativeMassScale": 1.0,
        "Friction": 0.8,
        "Restitution": 0.35,
        "Volume": 0.08099896,
        "Mass": 526.4932,
        "MassDistributionIndex": 0,
        "PhantomIndex": -1,
        "ProxyCollisionGroup": -1,
        "ShapeBase": {
          "FieldPointerSkip": {
            "Value": 0
          },
          "Size": 0,
          "Count": 128,
          "Userdata": {
            "Value": 32
          },
          "ShapeType": 8,
          "Radius": 0.0164
        },
        "AabbHalfExtents": "I: 0.4838073, J: 0.41147518, K: 0.10761663",
        "AabbHalfExtentsRadius": 0.0,
        "AabbCenter": "I: 2.9802322E-08, J: 0.0911399, K: -0.017950717",
        "AabbCenterRadius": 0.0,
        "FieldPointerSkip": {
          "Value": 0
        },
        "FourVectorsSize": 2,
        "FourVectorsCapacity": 2147483650,
        "NumVertices": 8,
        "AnotherFieldPointerSkip": {
          "Value": 0
        },
        "PlaneEquationsSize": 10,
        "PlaneEquationsCapacity": 2147483658,
        "Connectivity": 0
      }
    ],
    "PolyhedronFourVectors": [
      {
        "FourVectorsX": "I: -0.48380727, J: -0.48380727, K: -0.48380727",
        "FourVectorsXW": -0.48380727,
        "FourVectorsY": "I: -0.3203353, J: -0.024054058, K: 0.32022375",
        "FourVectorsYW": 0.32520503,
        "FourVectorsZ": "I: -0.029033152, J: 0.08966591, K: -0.06680959",
        "FourVectorsZW": 0.05040855
      },
      {
        "FourVectorsX": "I: 0.48380733, J: 0.48380733, K: 0.48380733",
        "FourVectorsXW": 0.48380733,
        "FourVectorsY": "I: -0.25626752, J: -0.22850668, K: 0.5026127",
        "FourVectorsYW": 0.5026151,
        "FourVectorsZ": "I: -0.027452698, J: 0.034332387, K: 0.050415687",
        "FourVectorsZW": -0.12556735
      }
    ],
    "PolyhedronPlaneEquations": [
      {
        "PlaneEquation": " Normal: I: -0.99999994, J: -0, K: 0, Distance:  -0.48380724"
      },
      {
        "PlaneEquation": " Normal: I: -0.18751767, J: 0.98137546, K: -0.04170434, Distance:  -0.4077684"
      },
      {
        "PlaneEquation": " Normal: I: -0.18033935, J: 0.98360443, K: 1.3271373E-05, Distance:  -0.40712327"
      },
      {
        "PlaneEquation": " Normal: I: -0.0494613, J: -0.05879981, K: -0.99704367, Distance:  -0.07171272"
      },
      {
        "PlaneEquation": " Normal: I: -0.025487501, J: -0.37177372, K: 0.92797345, Distance:  -0.10448129"
      },
      {
        "PlaneEquation": " Normal: I: -0.020482434, J: 0.11167502, K: 0.99353373, Distance:  -0.096309416"
      },
      {
        "PlaneEquation": " Normal: I: 0.01010914, J: -0.12821455, K: -0.991695, Distance:  -0.06497282"
      },
      {
        "PlaneEquation": " Normal: I: 0.052452374, J: -0.021962594, K: 0.9983819, Distance:  -0.06467228"
      },
      {
        "PlaneEquation": " Normal: I: 0.059620086, J: -0.9105333, K: 0.40911427, Distance:  -0.25095347"
      },
      {
        "PlaneEquation": " Normal: I: 0.99999994, J: -0, K: 0, Distance:  -0.4838073"
      }
    ],
    "MassDistributions": [],
    "Lists": [],
    "ListShapes": [],
    "Mopps": [],
    "MoppData": "",
    "HingeConstraints": [],
    "RagdollConstraints": [],
    "Regions": [
      {
        "Name": "hull",
        "Permutations": [
          {
            "Name": "base",
            "RigidBodies": [
              {
                "RigidBodyIndex": 0
              }
            ]
          }
        ]
      }
    ],
    "Nodes": [
      {
        "Name": "phantom_chunk_04",
        "Flags": 0,
        "Parent": -1,
        "Sibling": -1,
        "Child": -1
      }
    ],
    "LimitedHingeConstraints": [],
    "BallAndSocketConstraints": [],
    "Phantoms": []
  }
}